db_robust_clust/__init__.py
db_robust_clust/data.py
db_robust_clust/metrics.py
db_robust_clust/models.py
db_robust_clust/plots.py
db_robust_clust-0.1.5.dist-info/licenses/LICENSE
db_robust_clust-0.1.5.dist-info/METADATA
db_robust_clust-0.1.5.dist-info/WHEEL
db_robust_clust-0.1.5.dist-info/top_level.txt
db_robust_clust-0.1.5.dist-info/RECORD
