Metadata-Version: 2.4
Name: db-robust-clust
Version: 0.1.5
Summary: Apply distance based robust clustering for mixed data.
Home-page: https://github.com/FabioScielzoOrtiz/db_robust_clust
Author: Fabio Scielzo Ortiz
Author-email: fabio.scielzoortiz@gmail.com
Classifier: Programming Language :: Python :: 3
Classifier: License :: OSI Approved :: MIT License
Classifier: Operating System :: OS Independent
Requires-Python: >=3.7
License-File: LICENSE
Requires-Dist: polars
Requires-Dist: numpy<=1.26.4
Requires-Dist: PyDistances
Requires-Dist: pandas
Requires-Dist: scikit-learn-extra
Requires-Dist: tqdm
Requires-Dist: setuptools
Requires-Dist: pyarrow
Requires-Dist: matplotlib
Requires-Dist: seaborn
Dynamic: author
Dynamic: author-email
Dynamic: classifier
Dynamic: description
Dynamic: description-content-type
Dynamic: home-page
Dynamic: license-file
Dynamic: requires-dist
Dynamic: requires-python
Dynamic: summary
